Aliyun_apply/__init__.py
Aliyun_apply/up_down_loader.py
Aliyun_apply-1.0.3.dist-info/LICENSE.txt
Aliyun_apply-1.0.3.dist-info/METADATA
Aliyun_apply-1.0.3.dist-info/WHEEL
Aliyun_apply-1.0.3.dist-info/top_level.txt
Aliyun_apply-1.0.3.dist-info/zip-safe
Aliyun_apply-1.0.3.dist-info/RECORD
